price_loaders/__init__.py
price_loaders/tradingview.py
price_loaders-0.2.1.dist-info/METADATA
price_loaders-0.2.1.dist-info/WHEEL
price_loaders-0.2.1.dist-info/entry_points.txt
price_loaders-0.2.1.dist-info/licenses/LICENSE
price_loaders-0.2.1.dist-info/RECORD
