Metadata-Version: 2.4
Name: price-loaders
Version: 0.2.1
Summary: Add your description here
Author-email: prem <prem.ch@ku.th>
License-File: LICENSE
Requires-Python: >=3.11
Requires-Dist: pandas>=2.2.3
Requires-Dist: requests>=2.32.3
